Topsis-Shrey-102183040/__init__.py
Topsis-Shrey-102183040/__main__.py
topsisfile/__init__.py
topsisfile/__main__.py
Topsis_Shrey_102183040-1.0.4.dist-info/METADATA
Topsis_Shrey_102183040-1.0.4.dist-info/WHEEL
Topsis_Shrey_102183040-1.0.4.dist-info/entry_points.txt
Topsis_Shrey_102183040-1.0.4.dist-info/top_level.txt
Topsis_Shrey_102183040-1.0.4.dist-info/RECORD
