Metadata-Version: 2.1
Name: Topsis-Shrey-102183040
Version: 1.0.4
Summary: Compute Topsis scores and ranks for a given csv file using topsis method for multiple-criteria decision making(MCDM) 
Home-page: https://github.com/ShreySaxena24/Topsispy
Author: Shrey Saxena
Author-email: shrey.saxena.sms@gmail.com
License: MIT
Classifier: License :: OSI Approved :: MIT License
Classifier: Programming Language :: Python :: 3.6
Classifier: Programming Language :: Python :: 3.7
Classifier: Programming Language :: Python :: 3.8
Classifier: Programming Language :: Python :: 3.9
Classifier: Programming Language :: Python :: 3.10
Requires-Dist: Topsis-Shrey-102183040
